{
  "changes": [
    {
      "comment": "Change the way `TreeNodeItem` key is stored inside the object. Instead of using `extendedData`, now we use an undefined property on the `TreeNodeItem` itself. This should help us avoid the key being overwritten in the `extendedData` and makes `extendedData` usable for other purposes, e.g. storing some user's data.",
      "packageName": "@bentley/presentation-components",
      "type": "none"
    }
  ],
  "packageName": "@bentley/presentation-components",
  "email": "grigas.petraitis@bentley.com"
}